Metadata-Version: 2.1
Name: skibiditoilet231
Version: 0.0
Summary: skibiditoilet231
Author-email: applepro285@gmail.com
